leafmap_lite/__init__.py
leafmap_lite/leafmap_lite.py
leafmap_lite-0.1.0.dist-info/LICENSE
leafmap_lite-0.1.0.dist-info/METADATA
leafmap_lite-0.1.0.dist-info/WHEEL
leafmap_lite-0.1.0.dist-info/dependency_links.txt
leafmap_lite-0.1.0.dist-info/top_level.txt
leafmap_lite-0.1.0.dist-info/RECORD
